{
  "mhur31kbfgb5t": {
    "id": "mhur31kbfgb5t",
    "title": "network Survey",
    "category": "general",
    "questionCount": 4,
    "responseCount": 0,
    "createdAt": "2025-11-11T15:53:06.731Z",
    "isActive": true
  },
  "mhurechzgx57e": {
    "id": "mhurechzgx57e",
    "title": "network Survey",
    "category": "general",
    "questionCount": 8,
    "responseCount": 0,
    "createdAt": "2025-11-11T16:01:54.119Z",
    "isActive": true
  },
  "mhuryhbrcyk3b": {
    "id": "mhuryhbrcyk3b",
    "title": "network Survey",
    "category": "it",
    "questionCount": 6,
    "responseCount": 0,
    "createdAt": "2025-11-11T16:17:33.495Z",
    "isActive": true
  }
}
