{
  "id": "mhur31kbfgb5t",
  "title": "network Survey",
  "category": "general",
  "description": "",
  "questions": [
    {
      "id": 1,
      "question": "What security considerations should be taken when using cloud computing?",
      "type": "text",
      "required": true,
      "options": null
    },
    {
      "id": 2,
      "question": "What skills are needed to master cloud computing?",
      "type": "text",
      "required": true,
      "options": null
    },
    {
      "id": 3,
      "question": "How do you design a scalable web development solution?",
      "type": "text",
      "required": true,
      "options": null
    },
    {
      "id": 4,
      "question": "Which frameworks support cybersecurity implementation?",
      "type": "text",
      "required": true,
      "options": null
    }
  ],
  "settings": {
    "allowAnonymous": true,
    "collectEmail": true,
    "multipleSubmissions": true,
    "requireAll": true
  },
  "createdAt": "2025-11-11T15:53:06.731Z",
  "updatedAt": "2025-11-11T15:53:06.731Z",
  "responses": []
}
